sqlmesh_utils/__init__.py
sqlmesh_utils/_version.py
sqlmesh_utils/materializations/__init__.py
sqlmesh_utils/materializations/non_idempotent_incremental_by_time_range.py
sqlmesh_utils-0.1.1.dist-info/licenses/LICENSE
sqlmesh_utils-0.1.1.dist-info/METADATA
sqlmesh_utils-0.1.1.dist-info/WHEEL
sqlmesh_utils-0.1.1.dist-info/entry_points.txt
sqlmesh_utils-0.1.1.dist-info/top_level.txt
sqlmesh_utils-0.1.1.dist-info/RECORD
