Metadata-Version: 2.4
Name: sqlmesh-utils
Version: 0.1.1
Summary: Utilities for SQLMesh
Requires-Python: >=3.9
License-File: LICENSE
Requires-Dist: sqlmesh>=0.163.0
Provides-Extra: dev
Requires-Dist: pytest; extra == "dev"
Requires-Dist: pytest_mock; extra == "dev"
Requires-Dist: pytest_xdist; extra == "dev"
Requires-Dist: mypy~=1.13.0; extra == "dev"
Requires-Dist: pre-commit; extra == "dev"
Requires-Dist: ruff~=0.7.0; extra == "dev"
Requires-Dist: sqlmesh[trino]; extra == "dev"
Requires-Dist: sqlmesh[postgres]; extra == "dev"
Dynamic: license-file
